[
    {
        "资讯标题": "消息称苹果 iPad 12 下周发布：升级 A19 芯片 + 8GB RAM",
        "内容": "据外媒Mac Rumors报道，苹果计划于下周发布新款iPad，预计命名为“11英寸 iPad（A19）”。该产品外观将与iPad 11基本保持一致，但核心升级包括搭载A19芯片以支持Apple智能功能，运行内存从6GB提升至8GB。屏幕延续现款11英寸2360x1640分辨率LCD面板，并配备前后12MP摄像头。国行起售价预计为2999元。",
        "配图": [
            "https://img.ithome.com/newsuploadfiles/2026/2/e9c6d31b-4d3e-4f85-ae9f-38faaa943221.jpg?x-bce-process=image/quality,q_75/format,f_webp"
        ]
    },
    {
        "资讯标题": "华为 Mate 80 Pro 手机 16GB+512GB 规格开放购买：麒麟 9030 Pro 芯片，6999 元",
        "内容": "华为Mate 80 Pro手机16GB+512GB版本已开放购买，售价6999元，搭载麒麟9030 Pro芯片，性能较上代Mate 70 Pro最高提升42%。预计2026年3月15日前发货。购买渠道包括华为官网（仅晨曦金、云杉绿配色）和京东（全配色可选）。",
        "配图": [
            "https://img.ithome.com/newsuploadfiles/2026/2/6a44cc83-1137-4750-95d6-9d11e1c76846.jpg?x-bce-process=image/quality,q_75/format,f_webp"
        ]
    },
    {
        "资讯标题": "三星 Galaxy S26 / S26+ / S26 Ultra 系列新品发布会一文汇总：首发硬件防窥屏、谷歌“豆包手机”",
        "内容": "三星于2月26日发布Galaxy S26系列旗舰手机，包含S26、S26+及Ultra三款。最大亮点是Ultra版首发原生硬件防窥屏，可针对应用、通知及密码输入单独设置。全系搭载第五代骁龙8至尊版for Galaxy芯片，NPU、GPU及CPU性能均有显著提升。屏幕采用第二代动态AMOLED，支持1-120Hz刷新率与2600尼特峰值亮度，色深增至10bit。Ultra版配备200MP主摄及F1.4大光圈广角，影像系统升级，并支持S Pen。全系内置Galaxy AI功能。国内售价方面，S26起售价5499元（限时），S26+起售价8299元，S26 Ultra起售价10299元（限时）。同时发布Galaxy Buds4/4 Pro无线耳机，售价1399元与1899元。",
        "配图": [
            "https://img.ithome.com/newsuploadfiles/2026/2/44040078-b8ce-44f0-b137-238b5c73bfeb.jpg?x-bce-process=image/quality,q_75/format,f_webp/auto-orient,o_1"
        ]
    },
    {
        "资讯标题": "小米 AI 超轻薄旗舰笔记本曝光：Ultra 5 325/Ultra X7 358H 处理器，重量 1kg±",
        "内容": "IT之家报道，博主@数码闲聊站爆料小米将推出新款AI超轻薄旗舰笔记本。该笔记本预计配备14英寸屏幕，提供两种处理器配置：Intel Ultra 5 325（8核8线程，最高4.5GHz）和Ultra X7 358H（16核，最高4.8GHz，搭载锐炫B390核显），对应办公与全能不同定位。内存可选24GB+1TB或32GB+1TB，重量约为1公斤，主打极致便携。",
        "配图": [
            "https://img.ithome.com/newsuploadfiles/2026/2/7131160e-e37b-4007-bfcf-27426f2354fa.jpg?x-bce-process=image/quality,q_75/format,f_webp"
        ]
    },
    {
        "资讯标题": "苹果 iPhone 18 Pro 被曝正测试全新“深红色”，而折叠屏 iPhone 配色偏保守",
        "内容": "据彭博社马克·古尔曼爆料，苹果正为iPhone 18 Pro测试全新“深红色”配色，此举受iPhone 17 Pro系列“星宇橙”在中国市场巨大成功（被称为“爱马仕橙”）的启发。新配色得益于Pro系列铝合金一体成型机身提供的灵活着色空间。苹果也可能从咖啡色、紫色、酒红色中选一款作为年度主打色，若深红色落地，将是自iPhone 14后首次推出红色系，并首次应用于Pro机型。与此同时，苹果首款折叠屏iPhone（内部代号V68，预计2026年9月发布）配色策略极为保守，仅提供深灰/黑、白/浅银等基础色调，以简化生产流程，类似iPhone X发布时的策略。需注意，工程机测试配色未必最终量产。",
        "配图": [
            "https://img.ithome.com/newsuploadfiles/2026/2/75c89da7-4f44-465c-bf91-1e3fe66781da.png?x-bce-process=image/quality,q_75/format,f_webp"
        ]
    },
    {
        "资讯标题": "Nothing Phone (4a) Pro 手机细节曝光：后盖首次非透明，相机 140 倍变焦",
        "内容": "Nothing Phone (4a) Pro 手机细节曝光，将于3月5日发布。该机是Nothing首款取消整体透明后盖设计的机型，但摄像头区域与Glyph Matrix灯效系统仍保留在透明凸起结构中，并配备更大尺寸的灯条。影像方面，搭载5000万像素主摄及同规格长焦镜头，支持最高140倍变焦（标准版为70倍），另配800万像素超广角和3200万像素前置摄像头。核心配置采用骁龙7 Gen 4处理器，内置5400mAh电池，支持50W有线充电。标准版Phone (4a)则延续透明后盖，搭载骁龙7s Gen 4，长焦变焦能力较低。",
        "配图": [
            "https://img.ithome.com/newsuploadfiles/2026/2/1ec4dc0c-6fa4-41f3-bc12-1d31e09f7a2b.jpg?x-bce-process=image/quality,q_75/format,f_webp"
        ]
    },
    {
        "资讯标题": "消息称一加 15T 手机搭载 5000 万像素 85mm F2.8 潜望长焦，拥有无线充、7 开头大电池等特性",
        "内容": "据博主@数码闲聊站爆料，一加即将发布的小屏旗舰手机一加15T将搭载5000万像素85mm F2.8潜望长焦镜头，支持等效3.5倍光学变焦。此外，该机还具备窄边框设计、无线充电、满级防水、7000mAh以上大电池以及超声波指纹等特性。有用户质疑其可能取消超广角镜头，博主回应称因超广角启用率低，双摄方案更侧重长焦。该机被一加社区负责人称为“小屏党的梦中情机”，预计搭载骁龙8 Elite Gen5芯片，并于近期（可能为3月）发布。",
        "配图": [
            "https://img.ithome.com/newsuploadfiles/2026/2/bee60fe0-396d-42cf-aa4b-a40b3b857f85.jpg?x-bce-process=image/quality,q_75/format,f_webp"
        ]
    },
    {
        "资讯标题": "AMD Zen 7 Grimlock Ridge 桌面处理器渲染图曝光：最高 32 核",
        "内容": "消息源Moore's Law Is Dead曝光了AMD下一代Zen 7桌面处理器渲染图。旗舰型号代号“Grimlock Ridge”，最高配备32核，由两个16核CCD和一个IOD组成。此外还有16核的“Silverton”版本（频率或达7GHz）和精简规格的8核“Silverking”版本（不支持3D V-Cache，带宽减半）。该系列预计采用台积电1.4纳米A14工艺，计划2028年量产。AMD还计划将能效最佳的8核芯片用于移动端，推出“Grimlock Point”和“Grimlock Halo”笔记本处理器。",
        "配图": [
            "https://img.ithome.com/newsuploadfiles/2026/2/2ef88bec-74a8-4534-9641-ab4855cbcf95.jpg?x-bce-process=image/quality,q_75/format,f_webp"
        ]
    }
]